azure/mgmt/iothubprovisioningservices/__init__.py
azure/mgmt/iothubprovisioningservices/_configuration.py
azure/mgmt/iothubprovisioningservices/_iot_dps_client.py
azure/mgmt/iothubprovisioningservices/_version.py
azure/mgmt/iothubprovisioningservices/aio/__init__.py
azure/mgmt/iothubprovisioningservices/aio/_configuration.py
azure/mgmt/iothubprovisioningservices/aio/_iot_dps_client.py
azure/mgmt/iothubprovisioningservices/aio/operations/__init__.py
azure/mgmt/iothubprovisioningservices/aio/operations/_dps_certificate_operations.py
azure/mgmt/iothubprovisioningservices/aio/operations/_iot_dps_resource_operations.py
azure/mgmt/iothubprovisioningservices/aio/operations/_operations.py
azure/mgmt/iothubprovisioningservices/models/__init__.py
azure/mgmt/iothubprovisioningservices/models/_iot_dps_client_enums.py
azure/mgmt/iothubprovisioningservices/models/_models.py
azure/mgmt/iothubprovisioningservices/models/_models_py3.py
azure/mgmt/iothubprovisioningservices/operations/__init__.py
azure/mgmt/iothubprovisioningservices/operations/_dps_certificate_operations.py
azure/mgmt/iothubprovisioningservices/operations/_iot_dps_resource_operations.py
azure/mgmt/iothubprovisioningservices/operations/_operations.py
azure_mgmt_iothubprovisioningservices-1.0.0.dist-info/METADATA
azure_mgmt_iothubprovisioningservices-1.0.0.dist-info/WHEEL
azure_mgmt_iothubprovisioningservices-1.0.0.dist-info/top_level.txt
azure_mgmt_iothubprovisioningservices-1.0.0.dist-info/RECORD
